faust_tools/decorators.py
faust_tools/fields.py
faust_tools/response.py
faust_tools/serializer.py
faust_tools-1.0.8.dist-info/licenses/LICENSE
faust_tools-1.0.8.dist-info/METADATA
faust_tools-1.0.8.dist-info/WHEEL
faust_tools-1.0.8.dist-info/top_level.txt
faust_tools-1.0.8.dist-info/RECORD
