Metadata-Version: 2.4
Name: faust-tools
Version: 1.0.8
Summary: Faust Tools
Author-email: Biszx <isares.br@gmail.com>
License: MIT
Requires-Python: >=3.9
License-File: LICENSE
Requires-Dist: faust-streaming>=0.11.3
Dynamic: license-file
